secretsentry/__init__.py
secretsentry/cli.py
secretsentry/ml_detector.py
secretsentry/scanner.py
secretsentry-2.0.0.dist-info/licenses/LICENSE
secretsentry-2.0.0.dist-info/METADATA
secretsentry-2.0.0.dist-info/WHEEL
secretsentry-2.0.0.dist-info/entry_points.txt
secretsentry-2.0.0.dist-info/top_level.txt
secretsentry-2.0.0.dist-info/RECORD
