Metadata-Version: 2.4
Name: secretsentry
Version: 2.0.0
Summary: Advanced sensitive data scanner with Jupyter notebook support and intelligent false positive filtering
Author-email: Abdul Jilani <abdul.jilani@evolveailabs.com>
License: MIT
Project-URL: Homepage, https://github.com/y2ee201/secretsentry
Project-URL: Documentation, https://github.com/y2ee201/secretsentry#readme
Project-URL: Repository, https://github.com/y2ee201/secretsentry.git
Project-URL: Bug Tracker, https://github.com/y2ee201/secretsentry/issues
Keywords: security,secrets,scanner,pii,jupyter,notebook,api-keys,credentials,sanitization,privacy,devops,ci-cd,machine-learning,ml,transformers,false-positives
Classifier: Development Status :: 4 - Beta
Classifier: Intended Audience :: Developers
Classifier: Intended Audience :: System Administrators
Classifier: License :: OSI Approved :: MIT License
Classifier: Operating System :: OS Independent
Classifier: Programming Language :: Python :: 3
Classifier: Programming Language :: Python :: 3.7
Classifier: Programming Language :: Python :: 3.8
Classifier: Programming Language :: Python :: 3.9
Classifier: Programming Language :: Python :: 3.10
Classifier: Programming Language :: Python :: 3.11
Classifier: Programming Language :: Python :: 3.12
Classifier: Topic :: Security
Classifier: Topic :: Software Development :: Quality Assurance
Classifier: Topic :: System :: Systems Administration
Classifier: Topic :: Utilities
Requires-Python: >=3.7
License-File: LICENSE
Requires-Dist: tqdm>=4.62.0
Requires-Dist: numpy>=1.19.0
Provides-Extra: full
Requires-Dist: pandas>=1.3.0; extra == "full"
Requires-Dist: matplotlib>=3.3.0; extra == "full"
Requires-Dist: seaborn>=0.11.0; extra == "full"
Requires-Dist: ipywidgets>=7.6.0; extra == "full"
Requires-Dist: scikit-learn>=1.0.0; extra == "full"
Requires-Dist: transformers>=4.20.0; extra == "full"
Requires-Dist: torch>=1.11.0; extra == "full"
Requires-Dist: joblib>=1.1.0; extra == "full"
Provides-Extra: jupyter
Requires-Dist: ipywidgets>=7.6.0; extra == "jupyter"
Requires-Dist: pandas>=1.3.0; extra == "jupyter"
Requires-Dist: matplotlib>=3.3.0; extra == "jupyter"
Requires-Dist: seaborn>=0.11.0; extra == "jupyter"
Provides-Extra: analysis
Requires-Dist: pandas>=1.3.0; extra == "analysis"
Requires-Dist: matplotlib>=3.3.0; extra == "analysis"
Requires-Dist: seaborn>=0.11.0; extra == "analysis"
Provides-Extra: ml
Requires-Dist: scikit-learn>=1.0.0; extra == "ml"
Requires-Dist: joblib>=1.1.0; extra == "ml"
Requires-Dist: numpy>=1.19.0; extra == "ml"
Provides-Extra: ml-advanced
Requires-Dist: scikit-learn>=1.0.0; extra == "ml-advanced"
Requires-Dist: transformers>=4.20.0; extra == "ml-advanced"
Requires-Dist: torch>=1.11.0; extra == "ml-advanced"
Requires-Dist: joblib>=1.1.0; extra == "ml-advanced"
Requires-Dist: numpy>=1.19.0; extra == "ml-advanced"
Dynamic: license-file
